sodapclient/DASParser.py
sodapclient/DDSParser.py
sodapclient/Definitions.py
sodapclient/Handler.py
sodapclient/Parser.py
sodapclient/ProxyDict.py
sodapclient/VariableLoader.py
sodapclient/__init__.py
sodapclient/Examples/Example.py
sodapclient/Examples/__init__.py
sodapclient/Examples/proxyserver.txt
sodapclient/Tests/TestDASParser.py
sodapclient/Tests/TestDDSParser.py
sodapclient/Tests/TestParser.py
sodapclient/Tests/TestProxyDict.py
sodapclient/Tests/TestVariableLoader.py
sodapclient/Tests/__init__.py
sodapclient-0.3.0.dist-info/licenses/LICENSE.md
sodapclient-0.3.0.dist-info/METADATA
sodapclient-0.3.0.dist-info/WHEEL
sodapclient-0.3.0.dist-info/top_level.txt
sodapclient-0.3.0.dist-info/RECORD
