Metadata-Version: 2.4
Name: sodapclient
Version: 0.3.0
Summary: A simple OpenDAP client library
Home-page: https://github.com/marcuskd/sodapclient
Author: Marcus Donnelly
Author-email: marcus.k.donnelly@gmail.com
License: BSD 3-Clause
Keywords: OpenDAP,Environment,Science
Classifier: Development Status :: 3 - Alpha
Classifier: Intended Audience :: Science/Research
Classifier: Intended Audience :: Developers
Classifier: License :: OSI Approved :: MIT License
Classifier: Programming Language :: Python :: 3
Classifier: Topic :: Scientific/Engineering
License-File: LICENSE.md
Requires-Dist: numpy>=1.23
Dynamic: author
Dynamic: author-email
Dynamic: classifier
Dynamic: home-page
Dynamic: keywords
Dynamic: license
Dynamic: license-file
Dynamic: requires-dist
Dynamic: summary
